mkdocs_drawio_converter/__init__.py
mkdocs_drawio_converter/_version.py
mkdocs_drawio_converter/plugin.py
mkdocs_drawio_converter-1.1.4.dist-info/LICENSE
mkdocs_drawio_converter-1.1.4.dist-info/METADATA
mkdocs_drawio_converter-1.1.4.dist-info/WHEEL
mkdocs_drawio_converter-1.1.4.dist-info/entry_points.txt
mkdocs_drawio_converter-1.1.4.dist-info/top_level.txt
mkdocs_drawio_converter-1.1.4.dist-info/RECORD
