Metadata-Version: 2.1
Name: mkdocs-drawio-converter
Version: 1.1.4
Summary: MkDocs plugin to convert Drawio files to SVG format
Home-page: https://github.com/rajneesh-ril/mkdocs-drawio-converter
Author: Rajneesh Kumar/Subhanshu Shukla
Author-email: rajneesh.aggarwal@gmail.com
Project-URL: Bug Tracker, https://github.com/rajneesh-ril/mkdocs-drawio-converter/issues
Classifier: Programming Language :: Python :: 3
Classifier: Programming Language :: Python :: 3.7
Classifier: Programming Language :: Python :: 3.8
Classifier: Programming Language :: Python :: 3.9
Classifier: Programming Language :: Python :: 3.10
Classifier: License :: OSI Approved :: MIT License
Classifier: Operating System :: OS Independent
Classifier: Topic :: Documentation
Classifier: Topic :: Software Development :: Documentation
Requires-Python: >=3.7
License-File: LICENSE
Requires-Dist: mkdocs>=1.0.0
